{
  "generator-jhipster": {
    "applicationType": "monolith",
    "authenticationType": "jwt",
    "baseName": "telephone",
    "blueprints": [],
    "buildTool": "maven",
    "cacheProvider": "ehcache",
    "clientFramework": "react",
    "clientPackageManager": "npm",
    "clientTheme": "none",
    "clientThemeVariant": "",
    "creationTimestamp": 1656264529892,
    "databaseType": "sql",
    "devDatabaseType": "h2Disk",
    "devServerPort": 9060,
    "dtoSuffix": "DTO",
    "enableGradleEnterprise": false,
    "enableHibernateCache": true,
    "enableSwaggerCodegen": false,
    "enableTranslation": true,
    "entitySuffix": "",
    "jhiPrefix": "jhi",
    "jhipsterVersion": "7.8.1",
    "jwtSecretKey": "N2E3MWViZjExNzc2ZjRmOTNiZTQyMWQ4YzE0Y2RlNThkMjE2ZGNiYzE4N2RkMjQ0NjRhOTIzYmNiMGU1MWM0NGI3Y2M5ZTg4ZTY3NTcwMTU1NGFiNzMwMmYxYWFmYjYyY2MyMjMxY2JiMWQ4ZWE5NjI4NjdkMmQ4MzBiNWUzY2Y=",
    "languages": ["tr", "en"],
    "messageBroker": false,
    "nativeLanguage": "tr",
    "otherModules": [],
    "packageName": "com.telephone.app",
    "pages": [],
    "prodDatabaseType": "mysql",
    "reactive": false,
    "searchEngine": false,
    "serverPort": "8080",
    "serverSideOptions": [],
    "serviceDiscoveryType": "eureka",
    "skipCheckLengthOfIdentifier": false,
    "skipFakeData": false,
    "skipUserManagement": false,
    "testFrameworks": ["cypress"],
    "websocket": false,
    "withAdminUi": true
  }
}
